{
  "has_image": false,
  "parsing_res_list": [
    {
      "block_label": "text",
      "block_content": "(không được để ra ngoài mạch). Mỗi lần tiêm 0,25mg, ngày tiêm 0,5mg, cách 12 giờ tiêm 1 lần - Liều tối đa 1 lần/0,5mg, 24giờ/1mg."
    },
    {
      "block_label": "text",
      "block_content": "Chống chỉ định : Nhồi máu cơ tim- Viêm màng trong tim cấp-Dùng đồng thời với digitalin (phải nghỉ thuốc digitalin, ít nhất 3 ngày.)"
    },
    {
      "block_label": "text",
      "block_content": "Lưu ý : Tránh pha lẫn với các thuốc khác. Giảm liều nếu suy thận, suy hô hấp nặng vì gây giảm oxy máu."
    },
    {
      "block_label": "paragraph_title",
      "block_content": "Oxyboldin"
    },
    {
      "block_label": "text",
      "block_content": "Dạng thuốc : Viên sủi bọt có :"
    },
    {
      "block_label": "text",
      "block_content": "Boldin 0,0096mg"
    },
    {
      "block_label": "text",
      "block_content": "Na sulfat khan 0,54g"
    },
    {
      "block_label": "text",
      "block_content": "Mononatri phosphat 1,32mg"
    },
    {
      "block_label": "text",
      "block_content": "Natri bicarbonat 1,450g"
    },
    {
      "block_label": "text",
      "block_content": "Tác dụng : Thông mật, kháng acid, nhuận tràng."
    },
    {
      "block_label": "text",
      "block_content": "Chỉ định : Khó tiêu, trướng bụng, ợ, đầy hơi, buồn nôn, khó tiêu. Rát ống thực quản, thượng vị."
    },
    {
      "block_label": "text",
      "block_content": "Liều dùng : Uống 1 viên x 3 lần vào sáng, trưa, chiều hoặc vào lúc đau, khó chịu."
    },
    {
      "block_label": "text",
      "block_content": "Lưu ý : Tránh dùng nếu tắc đường mật - Có thể bị ỉa chảy (giảm liều)."
    },
    {
      "block_label": "paragraph_title",
      "block_content": "Ozothine (Pháp)"
    },
    {
      "block_label": "text",
      "block_content": "Dạng thuốc : Ống tiêm chứa 0,2% oxy hóa của tinh dầu thông, trong dung dịch glucose đẳng trương. Ống 10ml (người lớn), 5ml (trẻ em trở lên), 2ml (trẻ em dưới 6 tuổi)."
    },
    {
      "block_label": "text",
      "block_content": "Sirô, cứ 100ml có 0,2g các dẫn chất oxy hóa trên đây kèm 500mg dionin HCl, 7g Natri benzoat, 9g cồn 95o và 0,6g tinh dầu bạc hà - Lọ 125ml"
    },
    {
      "block_label": "text",
      "block_content": "Tác dụng : Sát khuẩn đường hô hấp, làm lỏng dịch tiết ở phế quản, tăng cường cung cấp oxy cho máu và các mô."
    },
    {
      "block_label": "text",
      "block_content": "Chỉ định : Các bệnh đường hô hấp cấp hoặc mạn, nhiễm khuẩn (có hoặc không phối hợp với kháng sinh) -Phòng bội nhiễm sau phẫu thuật phổi. Các bệnh đường hô hấp trên (Tai mũi họng)."
    },
    {
      "block_label": "text",
      "block_content": "Liều dùng : Tiêm tĩnh mạch hoặc bắp thịt 1-2 ống/ngày."
    },
    {
      "block_label": "text",
      "block_content": "Sirô : Người lớn uống ngày 3 lần, mỗi lần 1 thìa canh. Trẻ em từ 4-15 tuổi uống 3 lần, mỗi lần 1 thìa càfê."
    },
    {
      "block_label": "doc_title",
      "block_content": "P"
    },
    {
      "block_label": "paragraph_title",
      "block_content": "Paikinase (Pháp)"
    },
    {
      "block_label": "text",
      "block_content": "Dạng thuốc : Ống thuốc mỡ có 15g, có 5% cao tinh chế papain tan trong nước và 1,5% bacitracin (tương ứng với 50 đvqt/mg)."
    },
    {
      "block_label": "text",
      "block_content": "Tác dụng : Phối hợp thuốc kháng khuẩn với tác nhân làm sạch, mau lành vết thương."
    },
    {
      "block_label": "text",
      "block_content": "Chỉ định : Vết thương nhiễm khuẩn, áp xe, đinh, hậu bối, viêm tấy. Rửa vết thương với nước, muối đẳng trương, thấm khô, bôi 1 lớp mỏng thuốc, thay băng 1-2 lần/24giờ."
    },
    {
      "block_label": "paragraph_title",
      "block_content": "Pancreabil"
    },
    {
      "block_label": "text",
      "block_content": "Dạng thuốc : Viên nén bọc."
    },
    {
      "block_label": "text",
      "block_content": "Nội mô túi mật (phun sương) 192mg"
    },
    {
      "block_label": "text",
      "block_content": "Fenocinol 20mg"
    },
    {
      "block_label": "text",
      "block_content": "Tác dụng : Phối hợp dạng thuốc phủ tạng với thuốc chống co thắt ống dẫn mật."
    },
    {
      "block_label": "text",
      "block_content": "Chỉ định : Rối loạn chậm tiêu, kèm cảm giác đau : đầy bụng, nấc, buồn nôn..."
    },
    {
      "block_label": "text",
      "block_content": "Liều dùng : Ngày uống 3 lần, mỗi lần 2viên, vào bữa ăn."
    },
    {
      "block_label": "paragraph_title",
      "block_content": "Pancreatin"
    },
    {
      "block_label": "text",
      "block_content": "Biệt dược : Creon (Pháp)"
    },
    {
      "block_label": "text",
      "block_content": "Festale N(Roussel VN)"
    },
    {
      "block_label": "text",
      "block_content": "Nezym forte (Đức)"
    },
    {
      "block_label": "text",
      "block_content": "Neo- Panpur (Hungari)"
    },
    {
      "block_label": "text",
      "block_content": "Dạng thuốc : Viên nén, viên nang hay gói thuốc bột chứa 300-500mg hoặc 1g pancreatin."
    },
    {
      "block_label": "text",
      "block_content": "Tác dụng : Là dạng thuốc bào chế từ tuyến tụy của lợn, bò... dưới hình thức bột màu trắng hoặc vàng nhạt, chứa các men tiêu hóa ở tụy, như : trypsin, amylase và lipase."
    },
    {
      "block_label": "text",
      "block_content": "Chỉ định : Các chứng đầy bụng, chậm tiêu do suy tuyến tụy ở một số bệnh như viêm tụy, rối loạn gan- mật"
    },
    {
      "block_label": "text",
      "block_content": "Liều dùng : Người lớn, ngày uống 0.5-3g."
    },
    {
      "block_label": "number",
      "block_content": "504"
    }
  ]
}