{
  "has_image": false,
  "parsing_res_list": [
    {
      "block_label": "text",
      "block_content": "500 với nồng độ 1ml= 1KCal bằng cách thêm vào khoảng 125ml nước mỗi hộp."
    },
    {
      "block_label": "paragraph_title",
      "block_content": "Reptilase (Pháp)"
    },
    {
      "block_label": "text",
      "block_content": "Dạng thuốc : Ống tiêm 1ml (lấy từ nọc rắn làm đông máu). Chứa 1 đơn vị Klobusitzky hemmocoagulase."
    },
    {
      "block_label": "text",
      "block_content": "Tác dụng : Làm đông máu gồm 2 chất (một thành phần thromboplastin) và một thành phần gần giống như thrombin nhưng không bị heparin ức chế."
    },
    {
      "block_label": "text",
      "block_content": "Chỉ định : Điều trị chảy máu do phẫu thuật trong hoặc sau khi mổ, hoặc chảy máu nội khoa không do yếu tố đông máu."
    },
    {
      "block_label": "text",
      "block_content": "Liều dùng : Tiêm tĩnh mạch dưới da, bắp từ 1-3 ống/ngày."
    },
    {
      "block_label": "text",
      "block_content": "Chống chỉ định : Tiêm bắp nếu có hội chứng chảy máu sinh học, dị ứng với thuốc."
    },
    {
      "block_label": "paragraph_title",
      "block_content": "Rescinnamin"
    },
    {
      "block_label": "text",
      "block_content": "Reserpyle trimethoxycinnamate"
    },
    {
      "block_label": "text",
      "block_content": "Dạng thuốc : Viên nén 0,25-0,5mg"
    },
    {
      "block_label": "text",
      "block_content": "Tác dụng : Làm hạ huyết áp tương tự reserpin, nhưng dung nạp dễ dàng hơn. Thường dùng phối hợp như biệt dược sau đây :"
    },
    {
      "block_label": "text",
      "block_content": "Biệt dược : ISO- triraupin (Đức)"
    },
    {
      "block_label": "text",
      "block_content": "Dạng thuốc : Viên nén 70mg rescinnamin, 70mcg reserpin, 700mcg raubasin, và 3,3mg thiabrutazid (butizid)."
    },
    {
      "block_label": "text",
      "block_content": "Chỉ định : Các thể tăng huyết áp."
    },
    {
      "block_label": "text",
      "block_content": "Liều dùng Lúc đầu ngày 1/2 -1 viên, sau liều duy trì, ngày 1-2 viên."
    },
    {
      "block_label": "text",
      "block_content": "Chống chỉ định : Suy thận kèm vô niệu, mẫn cảm với sulfamid, giảm kali- huyết rõ rệt, hôn mê do gan, trầm cảm, phụ nữ có thai."
    },
    {
      "block_label": "text",
      "block_content": "Lưu ý : Tránh phối hợp với guanetidin, methyldopa."
    },
    {
      "block_label": "paragraph_title",
      "block_content": "Resemid (Bungari)"
    },
    {
      "block_label": "text",
      "block_content": "Dạng thuốc : Viên nén:"
    },
    {
      "block_label": "text",
      "block_content": "Reserpin 0,1mg"
    },
    {
      "block_label": "text",
      "block_content": "Furosemid 15mg"
    },
    {
      "block_label": "text",
      "block_content": "Tác dụng : Làm hạ huyết áp (đều đặn và dần dần)."
    },
    {
      "block_label": "text",
      "block_content": "Chỉ định : Các thể tăng huyết áp."
    },
    {
      "block_label": "text",
      "block_content": "Liều dùng : Trung bình : ngày 1-2 viên. Nếu nặng : có thể tới 3-4 viên ngày. Uống sau bữa ăn."
    },
    {
      "block_label": "text",
      "block_content": "Chống chỉ định : Mẫn cảm với 2 thành phần của thuốc, loét dạ dày- tá tràng tiến triển, trầm cảm, mất nước hoặc giảm thể tích máu, bệnh não gan, phụ nữ đang nuôi con bú."
    },
    {
      "block_label": "text",
      "block_content": "Biệt dược tương tự : Tenserlix (Pháp)"
    },
    {
      "block_label": "paragraph_title",
      "block_content": "Reserpin"
    },
    {
      "block_label": "text",
      "block_content": "Dạng thuốc : Viên nén 0,10mg và 0,25mg."
    },
    {
      "block_label": "text",
      "block_content": "Tác dụng : Là một alcaloid của cây Rauwolfia - Tác dụng làm hạ huyết áp."
    },
    {
      "block_label": "text",
      "block_content": "Chỉ định : Tặng huyết áp vô căn vừa phải nhất là khi kết hợp với thuốc trị tăng huyết áp khác (đặc biệt thuốc lợi tiểu) khi không dùng được liều cao."
    },
    {
      "block_label": "text",
      "block_content": "Liều dùng : Tùy từng người và liều tăng dần : bắt đầu 0,25-0,50mg/ngày. Có thể tăng lên 1-1,5mg/ngày, liều duy trì : 0,125mg- 0,25mg/ngày. Uống trong hay sau bữa ăn."
    },
    {
      "block_label": "text",
      "block_content": "Chống chỉ định : Trầm cảm (có ý đồ tự tử). Loét dạ dày- tá tràng. (nguy cơ chảy máu). Viêm loét đại tràng. Động kinh. Dùng phối hợp với IMAO. Có thai. Đang nuôi con bú."
    },
    {
      "block_label": "text",
      "block_content": "Lưu ý : Hết sức thận trọng với người trầm cảm. Nếu mất ngủ, kém ăn, bất lực, ý muốn tự tử thì ngừng thuốc. Thuốc làm buồn ngủ. Ngừng dùng thuốc ít ra 2 tuần nếu điều trị ngoại khoa, sốc điện. Không kết hợp với digitalin, quinidin và các thuốc chống loạn nhịp khác- Tránh dùng nếu suy tim, suy thận nặng."
    },
    {
      "block_label": "text",
      "block_content": "Tác dụng phụ: Rối loạn dạ dày- ruột (tăng tiết, buồn nôn, nôn, chán ăn, ỉa chảy)- nghẹt mũi, buồn ngủ, mệt mỏi, ác mộng, ưu tư, trầm cảm, giảm dục, bất lực, khó xuất tinh,