{
 "has_image": false,
 "parsing_res_list": [
  {
   "block_label": "text",
   "block_content": "Cây đuốc cá x. Thàn mát (Cây có độc)\nCây đậu ma x. Quyết minh Q4\nCây đề B12\nCây đết B12\nCây đuôi chồn x. Mào gà M3\nCây giang ông x. Huyết giác H25\nCây giấp suối x. Diếp cá suối D5\nCây gỗ vang x. Vang V2\nCây hóp x. Tinh tre T26\nCây hoa cựa x. Tộc tiên rừng M5\nCây lá giấp x. Diếp cá D5\nCây lan tiên x. Mạch môn đông M15\nCây lông cu ly x. Cẩu tích C10\nCây lức x. Sài hồ nam S5\nCây mào gà đuôi nheo x. Mào gà M3\nCây mắt trâu x. Vảy rồng V5\nCây muống canh x. Muồng trâu M21\nCây muồng ngủ x. Quyết minh Q4\nCây ngao x. Nhàu N14a\nCây óc chó x. Hồ đào H16\nCây quan âm x. Mạn kinh M6\nCây rụm x. Hồng hoa H19\nCây ruột gà B14\nCây sán lá x. Sơn tra S13\nCây sữa x. Sữa S15a\nCây sừng bò x. Hà thủ ô trắng\nCây sừng trâu x. Mộc hoa trắng M12\nCây thẹn x. Xấu hổ X1a\nCây thuốc cứu x. Ngải cứu N1\nCây thuốc dấu x. Nhân sâm VN N16\nCây thuốc lồm x. Thồm lồm T16a\nCây thuốc mộng x. Cỏ the C14a\nCây thuốc ôn x. Mạn kinh M6\nCây tổ phượng x. Cốt toái bổ C19\nCây tổ rồng x. Cốt toái bổ C19\nCây trăm chân x. Cỏ the C14a\nCây trúc cần câu T26a\nCây vó ngựa x. Mã đề M1\nCây vang nhuộm x. Vang V2\nCây xa x. Hột mát (xem cây có độc)\nCây xó nhà x. Huyết giác H25\nChàm lá to x. Chàm mèo C11\nChàm mèo C11\nChành chành x. Hậu phác H6\nChàng xuất đìa x. Ngọc trúc N7\nChân chim x. Ngũ gia bì chân chim N10\nChân vịt N10\nChấp C12\nChè cay x. Tràm T30\nChầu phỏng xì x. Ba kích B14\nChè đất S3\nChè đồng x. Tràm T30\nChè C12a\nChè hương C12a\nChè tàu C12a\nChẹo (xem cây có độc)\nChi dò x. Đào Đ7\nChiêu liêu x. Kha tử K2\nChi ma x. Vừng V6\nChi tử x. Dành dành D1\nChính hoài x. Củ mài C23\nChỉ thiên x. Mũi mác - Tiền hồ M20-T23\nChỉ thực x. Chấp C12\nChỉ xác x. Chấp C12\nChóc x. Bán hạ nam B16\nChói đèn x. Ích mẫu I1\nChổi sề x. Chổi C13\nChổi xuể x. Chổi sể C13\nChờ mờ mía x. Diếp cá D5\nChùm kết x. Bồ kết B26\nChùng xuất đĩa x. Ngọc trúc N7\nChương não L5\nChương thụ x. Long não L5\nChưởng diệp đại hoàng x. Đại hoàng Đ1\nCinchona C4a\nCo intó x. Cốt toái bổ C19\nCo mộc vài x. Mộc hoa trắng M12\nCo nam kho x. Câu đằng C9\nCo ngón x. Lá ngón (Xem Cây có độc)\nCo tạng tó x. Cốt toái bổ C19\nCo vầy mèo x. Diếp cá D5\nCóng khói x. Ba đậu B12\nCò cháy x. Thóc lép T15\nCò cú x. Cỏ gấu H30\nCỏ dùi trống x. Cốc tinh thảo C16\nCỏ đĩ x. Hy thiêm H31\nCỏ đuôi công x. Cốc tinh thảo C16\nCỏ gấu x. Hương phụ H30\nCỏ mật x. Hy thiêm H31\nCỏ mực x. Cỏ nhọ nồi N21\nCỏ nhọ nồi N21\nCỏ săng x. Cỏ tranh C15\nCỏ tai hồ C14\nCỏ tai hùm C14\nCỏ the C14a\nCỏ tóc tiên C14b\nCỏ tranh C15\nCỏ trói gà x. Bắt ruồi B18\nCỏ tỳ gà x. Bắt ruồi B18\nCóc mẳn x. Cỏ the C14a\nCóc ngồi x. Cỏ the C14a\nCoca C15a\nCola C17a\nCốc nha L9\nCốc tinh thảo x. Cỏ dùi trống C16\nCối xay C17\nCông toi x. Ba đậu B12\nCống truật x. Bạch truật B11\nCốt khí củ C18\nCốt khí hạt x. Cốt khí muồng C18\nCốt khí muồng C18\nCốt toái bổ C19\nCù lấc x. Ca cao C1a"
  },
  {
   "block_label": "number",
   "block_content": "665"
  }
 ]
}