{
 "has_image": false,
 "parsing_res_list": [
  {
   "block_label": "text",
   "block_content": "đau nhức mắt, nôn,chạy máu thì ngừng thuốc."
  },
  {
   "block_label": "text",
   "block_content": "- Tránh dùng : rối loạn niệu đạo - tiền liệt tuyến."
  },
  {
   "block_label": "doc_title",
   "block_content": "X"
  },
  {
   "block_label": "paragraph_title",
   "block_content": "X -Prep"
  },
  {
   "block_label": "text",
   "block_content": "Dạng thuốc : Gói bột 5g để uống có :"
  },
  {
   "block_label": "text",
   "block_content": "Cao khô phan tả diệp (đã chuẩn độ 54mg/g sennosid A và B) 2,4g"
  },
  {
   "block_label": "text",
   "block_content": "Kali sorbat 0,01g"
  },
  {
   "block_label": "text",
   "block_content": "Hương thơm 0,3g"
  },
  {
   "block_label": "text",
   "block_content": "Si dioxyd ngậm nước 0,005g"
  },
  {
   "block_label": "text",
   "block_content": "Đường kính 5g"
  },
  {
   "block_label": "text",
   "block_content": "Tác dụng : Tạo bài tiết ống tiêu hóa."
  },
  {
   "block_label": "text",
   "block_content": "Chỉ định : Chuẩn bị đại tràng để thụt dung dịch baryt hay soi đại tràng và trước khi chụp bộ niệu."
  },
  {
   "block_label": "text",
   "block_content": "Liều dùng : 1 gói dùng cho người 60kg tức 2mg sennosid/kg. Uống nhiều nước vào ngày trước khi khám nghiệm- Sau khi uống thuốc nên ăn nhẹ. Trong 3 ngày trước khi khám nghiệm, ăn các thức ăn không có cặn bã. Không dùng thuốc có Bi hay Ca."
  },
  {
   "block_label": "text",
   "block_content": "Chống chỉ định : Có thai- Trẻ em."
  },
  {
   "block_label": "paragraph_title",
   "block_content": "Xylitol"
  },
  {
   "block_label": "text",
   "block_content": "Biệt dược : Klinit (Nhật Bản)"
  },
  {
   "block_label": "text",
   "block_content": "Dạng thuốc : Dung dịch tiêm truyền xylitol dồng :"
  },
  {
   "block_label": "text",
   "block_content": "Lọ 500ml dd 5 và 10%."
  },
  {
   "block_label": "text",
   "block_content": "Ống tiêm 20ml dd 10-20 và 50%."
  },
  {
   "block_label": "text",
   "block_content": "Tác dụng : Xylitol, một đường pentose có chứa alcol, là một chất trung gian bình thường trong chuyển hóa glucid và được chuyển hóa qua đường pentose phosphat và acid uronic. Lượng xylitol từ ngoài đưa vào insulin và không làm tăng lượng đường trong máu, xylitol có hiệu lực cung cấp năng lượng kẻ cả trong trường hợp có rối loạn chuyển hóa glucid. Trong số các glucid, đó là chất có hiệu lực chống gây ceton - huyết mạnh nhất."
  },
  {
   "block_label": "text",
   "block_content": "Chỉ định : Để cải thiện rối loạn chuyền hóa glucid ở bệnh nhân đái tháo đường. Bổ sung cung cấp năng lượng cho cơ thể."
  },
  {
   "block_label": "text",
   "block_content": "Liều dùng : Với dd 10-20%, tiêm tĩnh mạch với liều tương ứng 2-30g xylitol, dùng đơn thuần hoặc phối hợp với các thuốc khác, chia 1-3 lần/ngày."
  },
  {
   "block_label": "text",
   "block_content": "Để tiêm truyền tĩnh mạch dùng dd 5% đơn thuần hoặc phối hợp với dd NaCl điện giải : Lượng dùng 24 giờ không quá 100g xylitol. Tốc độ tiêm truyền không quá 0,5g xylitol/kg/giờ."
  },
  {
   "block_label": "text",
   "block_content": "Lưu ý : Nếu dd quá lạnh, cần hâm nóng dd đến nhiệt độ cơ thế trước khi tiêm"
  },
  {
   "block_label": "doc_title",
   "block_content": "Y"
  },
  {
   "block_label": "paragraph_title",
   "block_content": "Y. K. (Đài Loan)"
  },
  {
   "block_label": "text",
   "block_content": "Dạng thuốc : Hộp 30 viên nang, mỗi nang chứa :"
  },
  {
   "block_label": "text",
   "block_content": "Metyltestosteron 5mg"
  },
  {
   "block_label": "text",
   "block_content": "Thiamin monitrat 10mg"
  },
  {
   "block_label": "text",
   "block_content": "Riboflavin 2mg"
  },
  {
   "block_label": "text",
   "block_content": "Pyridoxin HCl 2mg"
  },
  {
   "block_label": "text",
   "block_content": "Cervus sika 2mg"
  },
  {
   "block_label": "text",
   "block_content": "Hoelen ext (bột) 60mg"
  },
  {
   "block_label": "text",
   "block_content": "Khởi tử (bột) 24mg"
  },
  {
   "block_label": "text",
   "block_content": "Nhân sâm (bột) 24mg"
  },
  {
   "block_label": "text",
   "block_content": "Đỗ trọng (bột) 60mg"
  },
  {
   "block_label": "text",
   "block_content": "Achyranthes Radix ext (bột) 50mg"
  },
  {
   "block_label": "text",
   "block_content": "Dioscoreae Radix ext (bột) 50mg"
  },
  {
   "block_label": "text",
   "block_content": "Ligustri Fructus (bột) 50mg"
  },
  {
   "block_label": "text",
   "block_content": "Polygonati falcti rhizoma ext.(bột) 50mg"
  },
  {
   "block_label": "text",
   "block_content": "Hoàng kỳ ext (bột) 60mg"
  },
  {
   "block_label": "text",
   "block_content": "Chỉ định : Các rối loạn ở người có tuổi như suy yếu, giảm thị lực, khó ngủ, mệt mỏi đau lưng, suy nhược thần kinh."
  },
  {
   "block_label": "number",
   "block_content": "580"
  }
 ]
}